tamm/__init__.py
tamm/_compat.py
tamm/_helpers.py
tamm/_logger.py
tamm/_version.py
tamm/_version_guidance.py
tamm/_warnings.py
tamm/runtime_configuration.py
tamm/typing.py
tamm/_adapters_v1/__init__.py
tamm/_adapters_v1/adapted_layer.py
tamm/_adapters_v1/adapter_api.py
tamm/_adapters_v1/layer_annotations.py
tamm/_adapters_v1/shared_context.py
tamm/_adapters_v1/utils.py
tamm/_adapters_v1/layer_adapters/__init__.py
tamm/_adapters_v1/layer_adapters/average.py
tamm/_adapters_v1/layer_adapters/bottleneck.py
tamm/_adapters_v1/layer_adapters/common.py
tamm/_adapters_v1/layer_adapters/lora.py
tamm/_adapters_v1/layer_adapters/prefix_tuning.py
tamm/_adapters_v1/layer_adapters/soft_mixing_lora.py
tamm/_adapters_v1/layer_adapters/stack.py
tamm/_adapters_v1/model_adapters/__init__.py
tamm/_adapters_v1/model_adapters/bottleneck.py
tamm/_adapters_v1/model_adapters/composition.py
tamm/_adapters_v1/model_adapters/lora.py
tamm/_adapters_v1/model_adapters/model_adapter.py
tamm/_cli/__init__.py
tamm/_cli/__main__.py
tamm/_cli/clean.py
tamm/_cli/common.py
tamm/_cli/from_tamm.py
tamm/_cli/ls.py
tamm/_cli/show.py
tamm/_cli/to_tamm.py
tamm/_cli/version.py
tamm/_cli/_listers/__init__.py
tamm/_cli/_listers/_base.py
tamm/_cli/_listers/_helpers.py
tamm/_cli/_listers/converters.py
tamm/_cli/_listers/models.py
tamm/_cli/_listers/preprocessors.py
tamm/_cli/_listers/tokenizers.py
tamm/_ops/__init__.py
tamm/_ops/segment_matmul/__init__.py
tamm/_ops/segment_matmul/interface.py
tamm/_ops/segment_matmul/torch.py
tamm/_ops/segment_matmul/triton_kernels.py
tamm/_ops/segment_matmul/triton_wrappers.py
tamm/_plugin/__init__.py
tamm/_plugin/cli.py
tamm/_plugin/core_import_callback.py
tamm/_plugin/core_transformers_import_callback.py
tamm/_plugin/utils.py
tamm/adapters/__init__.py
tamm/adapters/utils/__init__.py
tamm/ao/__init__.py
tamm/ao/utils.py
tamm/ao/arch_optimizers/__init__.py
tamm/ao/arch_optimizers/common.py
tamm/ao/arch_optimizers/kv_quant.py
tamm/ao/arch_optimizers/low_rank_embeddings_svd.py
tamm-0.2.0.dist-info/licenses/LICENSE.md
tamm-0.2.0.dist-info/METADATA
tamm-0.2.0.dist-info/WHEEL
tamm-0.2.0.dist-info/entry_points.txt
tamm-0.2.0.dist-info/top_level.txt
tamm-0.2.0.dist-info/RECORD
