Metadata-Version: 2.4
Name: tamm
Version: 0.2.0
Summary: A library for ML model development with PyTorch
License-Expression: MIT
Keywords: Machine learning,Model development,PyTorch,Natural language processing,Computer vision,Audio processing,Transformers,Deep learning,Generative AI
Classifier: Intended Audience :: Developers
Requires-Python: >=3.9
License-File: LICENSE.md
Requires-Dist: torch>=2.1
Requires-Dist: numpy
Requires-Dist: jinja2
Requires-Dist: filelock
Requires-Dist: wrapt
Requires-Dist: packaging
Requires-Dist: coloredlogs
Provides-Extra: sentencepiece
Requires-Dist: sentencepiece; extra == "sentencepiece"
Provides-Extra: transformers
Requires-Dist: transformers; extra == "transformers"
Requires-Dist: safetensors; extra == "transformers"
Provides-Extra: xxhash
Requires-Dist: xxhash; extra == "xxhash"
Provides-Extra: torchvision
Requires-Dist: torchvision; extra == "torchvision"
Provides-Extra: all
Requires-Dist: tamm[sentencepiece,torchvision,transformers,xxhash]; extra == "all"
Dynamic: license-file
